lruun/__init__.py
lruun/tf/__init__.py
lruun/tf/geglu.py
lruun/tf/linear_recurrent_unit.py
lruun-0.0.2.dist-info/LICENSE
lruun-0.0.2.dist-info/METADATA
lruun-0.0.2.dist-info/WHEEL
lruun-0.0.2.dist-info/top_level.txt
lruun-0.0.2.dist-info/RECORD
