Metadata-Version: 2.1
Name: lruun
Version: 0.0.2
Summary: LRU TensorFlow implementation
Home-page: https://github.com/lucehe/lru_unofficial
Author: Luca Herrtti
Author-email: luca.herrtti@gmail.com
License: MIT
Project-URL: Bug Tracker, https://github.com/lucehe/lru_unofficial/issues
Classifier: Development Status :: 3 - Alpha
Classifier: Programming Language :: Python :: 3 :: Only
Classifier: License :: OSI Approved :: MIT License
Classifier: Operating System :: OS Independent
Requires-Python: >=3.9
License-File: LICENSE
Requires-Dist: tensorflow (==2.10.0)
Requires-Dist: tensorflow-probability (==0.18.0)
